elementembeddings/__init__.py
elementembeddings/_base.py
elementembeddings/composition.py
elementembeddings/core.py
elementembeddings/plotter.py
elementembeddings/data/element_data/element_group.json
elementembeddings/data/element_data/element_symbols.json
elementembeddings/data/element_data/ordered_periodic.txt
elementembeddings/data/element_data/periodic-table-lookup-symbols.json
elementembeddings/data/element_data/periodic-table-lookup.json
elementembeddings/data/element_representations/atomic.json
elementembeddings/data/element_representations/cgnf.json
elementembeddings/data/element_representations/crystallm_v24c.dim512_atom_vectors.csv
elementembeddings/data/element_representations/magpie.csv
elementembeddings/data/element_representations/magpie_sc.json
elementembeddings/data/element_representations/mat2vec.csv
elementembeddings/data/element_representations/matscholar-embedding.json
elementembeddings/data/element_representations/megnet16.json
elementembeddings/data/element_representations/mod_petti.json
elementembeddings/data/element_representations/oliynyk.csv
elementembeddings/data/element_representations/oliynyk_preprocessed.csv
elementembeddings/data/element_representations/oliynyk_sc.json
elementembeddings/data/element_representations/random_200.csv
elementembeddings/data/element_representations/random_200_new.csv
elementembeddings/data/element_representations/skipatom_20201009_induced.csv
elementembeddings/data/element_representations/xenonpy_element_features.csv
elementembeddings/data/species_representations/skipspecies_2022_10_28_dim200.csv
elementembeddings/data/species_representations/skipspecies_2022_10_28_induced_dim200.csv
elementembeddings/tests/__init__.py
elementembeddings/tests/test_composition.py
elementembeddings/tests/test_core.py
elementembeddings/tests/test_plotter.py
elementembeddings/tests/test_utils.py
elementembeddings/utils/__init__.py
elementembeddings/utils/config.py
elementembeddings/utils/io.py
elementembeddings/utils/math.py
ElementEmbeddings-0.6.1.dist-info/LICENSE.md
ElementEmbeddings-0.6.1.dist-info/METADATA
ElementEmbeddings-0.6.1.dist-info/WHEEL
ElementEmbeddings-0.6.1.dist-info/top_level.txt
ElementEmbeddings-0.6.1.dist-info/RECORD
