Metadata-Version: 2.1
Name: ElementEmbeddings
Version: 0.6.1
Summary: Element Embeddings
Author: Anthony O. Onwuli
Author-email: anthony.onwuli16@imperial.ac.uk
Classifier: Programming Language :: Python
Classifier: Programming Language :: Python :: 3.9
Classifier: Programming Language :: Python :: 3.10
Classifier: Programming Language :: Python :: 3.11
Classifier: Programming Language :: Python :: 3.12
Classifier: Development Status :: 4 - Beta
Classifier: Intended Audience :: Science/Research
Classifier: Operating System :: OS Independent
Classifier: Topic :: Scientific/Engineering
Classifier: Topic :: Scientific/Engineering :: Chemistry
Classifier: License :: OSI Approved :: MIT License
License-File: LICENSE.md
Requires-Dist: numpy <3,>=1.23.3
Requires-Dist: scipy >=1.10.1
Requires-Dist: pymatgen >2022.9.21
Requires-Dist: seaborn >=0.13.0
Requires-Dist: matplotlib >=3.7.1
Requires-Dist: scikit-learn >=1.3.0
Requires-Dist: umap-learn >=0.5.3
Requires-Dist: adjustText >=0.8
Requires-Dist: openTSNE >=1.0.0
Requires-Dist: typing-extensions
Provides-Extra: dev
Requires-Dist: pre-commit ; extra == 'dev'
Requires-Dist: black ; extra == 'dev'
Requires-Dist: isort ; extra == 'dev'
Requires-Dist: pytest ; extra == 'dev'
Requires-Dist: pytest-subtests ; extra == 'dev'
Requires-Dist: nbqa ; extra == 'dev'
Requires-Dist: flake8 ; extra == 'dev'
Requires-Dist: pyupgrade ; extra == 'dev'
Requires-Dist: autopep8 ; extra == 'dev'
Requires-Dist: pytest-cov ; extra == 'dev'
Requires-Dist: pytest-mpl ; extra == 'dev'
Provides-Extra: docs
Requires-Dist: mkdocs ; extra == 'docs'
Requires-Dist: mkdocs-material ; extra == 'docs'
Requires-Dist: mkdocstrings ; extra == 'docs'
Requires-Dist: mkdocstrings-python ; extra == 'docs'
Requires-Dist: mike ; extra == 'docs'
Requires-Dist: mkdocs-jupyter ; extra == 'docs'
